LICENSE
README.md
setup.py
FlagEmbedding/__init__.py
FlagEmbedding.egg-info/PKG-INFO
FlagEmbedding.egg-info/SOURCES.txt
FlagEmbedding.egg-info/dependency_links.txt
FlagEmbedding.egg-info/requires.txt
FlagEmbedding.egg-info/top_level.txt
FlagEmbedding/abc/__init__.py
FlagEmbedding/abc/evaluation/__init__.py
FlagEmbedding/abc/evaluation/arguments.py
FlagEmbedding/abc/evaluation/data_loader.py
FlagEmbedding/abc/evaluation/evaluator.py
FlagEmbedding/abc/evaluation/runner.py
FlagEmbedding/abc/evaluation/searcher.py
FlagEmbedding/abc/evaluation/utils.py
FlagEmbedding/abc/finetune/__init__.py
FlagEmbedding/abc/finetune/embedder/AbsArguments.py
FlagEmbedding/abc/finetune/embedder/AbsDataset.py
FlagEmbedding/abc/finetune/embedder/AbsModeling.py
FlagEmbedding/abc/finetune/embedder/AbsRunner.py
FlagEmbedding/abc/finetune/embedder/AbsTrainer.py
FlagEmbedding/abc/finetune/embedder/__init__.py
FlagEmbedding/abc/finetune/reranker/AbsArguments.py
FlagEmbedding/abc/finetune/reranker/AbsDataset.py
FlagEmbedding/abc/finetune/reranker/AbsModeling.py
FlagEmbedding/abc/finetune/reranker/AbsRunner.py
FlagEmbedding/abc/finetune/reranker/AbsTrainer.py
FlagEmbedding/abc/finetune/reranker/__init__.py
FlagEmbedding/abc/inference/AbsEmbedder.py
FlagEmbedding/abc/inference/AbsReranker.py
FlagEmbedding/abc/inference/__init__.py
FlagEmbedding/evaluation/__init__.py
FlagEmbedding/evaluation/air_bench/__init__.py
FlagEmbedding/evaluation/air_bench/__main__.py
FlagEmbedding/evaluation/air_bench/arguments.py
FlagEmbedding/evaluation/air_bench/runner.py
FlagEmbedding/evaluation/beir/__init__.py
FlagEmbedding/evaluation/beir/__main__.py
FlagEmbedding/evaluation/beir/arguments.py
FlagEmbedding/evaluation/beir/data_loader.py
FlagEmbedding/evaluation/beir/evaluator.py
FlagEmbedding/evaluation/beir/prompts.py
FlagEmbedding/evaluation/beir/runner.py
FlagEmbedding/evaluation/custom/__init__.py
FlagEmbedding/evaluation/custom/__main__.py
FlagEmbedding/evaluation/custom/data_loader.py
FlagEmbedding/evaluation/custom/runner.py
FlagEmbedding/evaluation/miracl/__init__.py
FlagEmbedding/evaluation/miracl/__main__.py
FlagEmbedding/evaluation/miracl/data_loader.py
