Metadata-Version: 2.1
Name: FlagEmbedding
Version: 1.3.5
Summary: FlagEmbedding
Home-page: https://github.com/FlagOpen/FlagEmbedding
Author-email: 2906698981@qq.com
License: UNKNOWN
Platform: UNKNOWN
License-File: LICENSE
Requires-Dist: torch>=1.6.0
Requires-Dist: transformers>=4.44.2
Requires-Dist: datasets>=2.19.0
Requires-Dist: accelerate>=0.20.1
Requires-Dist: sentence_transformers
Requires-Dist: peft
Requires-Dist: ir-datasets
Requires-Dist: sentencepiece
Requires-Dist: protobuf
Provides-Extra: finetune
Requires-Dist: deepspeed; extra == "finetune"
Requires-Dist: flash-attn; extra == "finetune"
